{
  "schema_version": "1.0",
  "product_name": "ShieldMendAi",
  "workspace_path": "/root/ShieldMendAi",
  "source_path": "/root/newbasebot",
  "updated_at_utc": "2026-06-25T17:50:02Z",
  "current_phase": "Phase 6 - safe incident records, retention controls, and deterministic notification simulation complete",
  "files_created": [
    "src/shieldmendai/incidents.py",
    "src/shieldmendai/notifications.py",
    "tests/test_phase6.py",
    "docs/INCIDENTS_AND_NOTIFICATIONS.md",
    "examples/incidents/incident-low.json",
    "examples/notifications/policy.yaml",
    "examples/notifications/template.yaml",
    "examples/notifications/scenario.yaml",
    "examples/retention/policy.yaml",
    "examples/retention/scenario.yaml"
  ],
  "files_changed": [
    ".gitignore",
    "src/shieldmendai/errors.py",
    "src/shieldmendai/cli.py",
    "README.md",
    "INSTALL.md",
    "PROJECT_STATUS.md",
    "docs/ARCHITECTURE.md",
    "docs/CONFIGURATION.md",
    "docs/EXTRACTION_PLAN.md",
    "docs/SECURITY_BOUNDARIES.md",
    "docs/CODEX_HANDOFF.md",
    "extraction_manifest.json"
  ],
  "implemented_features": [
    "typed versioned incident records, summaries, evidence references, target references, timelines, outcomes, and store metadata",
    "explicit incident lifecycle transition allowlist with closed and manual-intervention protections",
    "deterministic exact-scope correlation and canonical duplicate references",
    "sanitized-content checksum validation and chronological unique event enforcement",
    "temporary-root-confined atomic local JSON incident store",
    "deterministic retention preview and explicit temporary-fixture removal simulation",
    "fixed notification provider capabilities and duplicate-safe registry",
    "Telegram, email, SMS, webhook, and local deterministic delivery simulations",
    "severity, event, status, and escalation notification routing",
    "allowlisted notification templates with safe rendering, redaction, escaping, bounds, and visible truncation",
    "exact duplicate-alert suppression, deterministic cooldowns, and finite attempt budgets",
    "typed route, suppression, attempt, delivery, batch, and audit records",
    "Phase 6 inspection, rendering, preview, and simulation CLI commands"
  ],
  "incident_states": [
    "detected",
    "open",
    "acknowledged",
    "investigating",
    "remediation_planned",
    "simulated_recovery_running",
    "monitoring_verification",
    "resolved",
    "closed",
    "suppressed",
    "duplicate",
    "manual_intervention_required"
  ],
  "incident_event_types": [
    "incident_created",
    "finding_recorded",
    "severity_changed",
    "status_changed",
    "incident_acknowledged",
    "remediation_recommended",
    "repair_authorized",
    "repair_denied",
    "simulated_repair_started",
    "simulated_repair_completed",
    "verification_started",
    "verification_succeeded",
    "verification_failed",
    "rollback_required",
    "rollback_completed",
    "rollback_failed",
    "circuit_opened",
    "manual_intervention_requested",
    "notification_planned",
    "notification_suppressed",
    "notification_simulated",
    "incident_resolved",
    "incident_closed",
    "incident_marked_duplicate",
    "retention_previewed",
    "retention_simulated"
  ],
  "local_store_features": [
    "explicit existing temporary root required",
    "absolute production roots rejected",
    "path traversal and symlink escape rejected",
    "atomic JSON writes within the validated root",
    "integrity inspection and deterministic listing",
    "no default production incident directory"
  ],
  "retention_features": [
    "maximum age, record count, and total bytes modeling",
    "unresolved, manual-intervention, severity, and latest-version protections",
    "preview-only default",
    "supplied deterministic clock",
    "explicit generated-fixture removal simulation only",
    "sanitized retention audit records"
  ],
  "notifier_types": [
    "telegram",
    "email",
    "sms",
    "webhook",
    "local",
    "none"
  ],
  "routing_features": [
    "exact configured channel IDs",
    "severity routes",
    "event routes",
    "status routes",
    "manual-intervention, rollback-failure, and circuit-open escalation",
    "target and category suppression",
    "provider failure isolation",
    "production delivery unavailable"
  ],
  "template_features": [
    "fixed sanitized variable allowlist",
    "unknown variable, attribute access, indexing, conversion, and filter rejection",
    "provider-specific escaping",
    "message length limits and visible truncation",
    "simulation-only labeling",
    "no evidence object rendering or secret resolution"
  ],
  "suppression_features": [
    "exact sanitized fingerprints",
    "duplicate windows",
    "severity escalation override by explicit policy",
    "manual-intervention override by explicit policy",
    "deterministic cooldown and next eligible timestamp",
    "per-channel and per-incident attempt budgets",
    "no sleeps or background tasks"
  ],
  "tests_run": [
    "Phase 5 baseline: PYTHONPATH=src python3 -m unittest discover -s tests -v - 118 tests passed",
    "Phase 6 focused: PYTHONPATH=src python3 -m unittest tests.test_phase6 -q - 23 tests passed",
    "Phase 6 complete regression: PYTHONPATH=src python3 -m unittest discover -s tests -v - 141 tests passed",
    "python3 -m compileall -q src tests",
    "Phase 5 baseline wheel build succeeded",
    "Phase 6 final wheel build produced shieldmendai-0.4.0-py3-none-any.whl"
  ],
  "checks_run": [
    "exact workspace and official origin verification",
    "official origin fetch without branch modification",
    "clean Phase 5 baseline and exact local/remote Phase 5 tip match",
    "Phase 5 resume check",
    "Phase 5 baseline test, compilation, and wheel build",
    "Phase 6 focused incident, store, integrity, retention, notification, rendering, routing, suppression, cooldown, limit, isolation, and CLI tests",
    "manifest and example incident JSON validation",
    "Git whitespace check",
    "temporary-root confinement and unrelated-file preservation"
  ],
  "prohibited_capabilities": [
    "real Telegram, email, SMS, webhook, or local production notification delivery",
    "provider authentication, environment-secret resolution, or credential loading",
    "socket, DNS, HTTP, HTTPS, SMTP, TCP, subprocess, or shell execution",
    "production incident storage or retention deletion",
    "live systemd, process, monitoring, verification, repair, recovery, rollback, or deployment",
    "service restart, file restoration, permission or ownership mutation",
    "package, firewall, certificate, database, Docker, Kubernetes, or Windows service mutation",
    "remote telemetry, incident upload, central-cloud storage, or customer-data transmission",
    "eval, exec, pickle, dynamic plugins, background delivery loops, or real-time sleeps"
  ],
  "source_safety_result": "passed; Phase 6 did not access, inspect, hash, search, copy, or modify /root/newbasebot and used only sanitized repository records",
  "last_commit": "87fc06f",
  "implementation_commit": "87fc06f",
  "documentation_checkpoint": "pending",
  "remote_status": "origin is exactly https://github.com/shieldmendai/shieldmendai-core; Phase 6 branch push pending",
  "push_status": "pending commits and push",
  "next_actions": [
    "Create a controlled dedicated-server sandbox installation and a local-only, read-only Linux observation pilot for ShieldMendAi",
    "Do not begin Phase 7 in the Phase 6 run"
  ],
  "blockers": []
}
